{
	"configurations" : 
	[
		{
			"directories" : 
			[
				{
					"build" : ".",
					"jsonFile" : "directory-.-Debug-d0094a50bb2071803777.json",
					"minimumCMakeVersion" : 
					{
						"string" : "3.21"
					},
					"projectIndex" : 0,
					"source" : ".",
					"targetIndexes" : 
					[
						0
					]
				}
			],
			"name" : "Debug",
			"projects" : 
			[
				{
					"directoryIndexes" : 
					[
						0
					],
					"name" : "Creator",
					"targetIndexes" : 
					[
						0
					]
				}
			],
			"targets" : 
			[
				{
					"directoryIndex" : 0,
					"id" : "Creator::@6890427a1f51a3e7e1df",
					"jsonFile" : "target-Creator-Debug-f3b8700b49975427d556.json",
					"name" : "Creator",
					"projectIndex" : 0
				}
			]
		}
	],
	"kind" : "codemodel",
	"paths" : 
	{
		"build" : "C:/C++/ОСИ/1 лаба/Creator/cmake-build-debug",
		"source" : "C:/C++/ОСИ/1 лаба/Creator"
	},
	"version" : 
	{
		"major" : 2,
		"minor" : 3
	}
}
